[
    {
        "path": [
            {
                "latitude": 33.4484,
                "name": "Phoenix, AZ",
                "longitude": -112.074
            },
            {
                "latitude": 32.2226,
                "name": "Tucson, AZ",
                "longitude": -110.9747
            }
        ],
        "distanceMiles": 106.04557316230664,
        "name": "Route 1",
        "distanceKm": 170.66385969462146,
        "time": 3.5348524387435547
    },
    {
        "path": [
            {
                "latitude": -33.8688,
                "name": "Sydney, Australia",
                "longitude": 151.2093
            },
            {
                "latitude": -37.8136,
                "name": "Melbourne, Australia",
                "longitude": 144.9631
            }
        ],
        "distanceMiles": 443.3031471225441,
        "name": "Route 2",
        "distanceKm": 713.4274807201239,
        "time": 14.77677157075147
    },
    {
        "path": [
            {
                "latitude": 35.6895,
                "name": "Tokyo, Japan",
                "longitude": 139.6917
            },
            {
                "latitude": 37.5665,
                "name": "Seoul, South Korea",
                "longitude": 126.978
            }
        ],
        "distanceMiles": 716.2035597497617,
        "name": "Route 3",
        "distanceKm": 1152.6182582543468,
        "time": 23.873451991658722
    },
    {
        "path": [
            {
                "latitude": 33.4484,
                "name": "Start",
                "longitude": -112.074
            },
            {
                "latitude": 33.4418,
                "name": "End",
                "longitude": -111.943
            }
        ],
        "distanceMiles": 7.566223611468313,
        "name": "Morning Coffee Run",
        "distanceKm": 12.17666033894133,
        "time": 0.25220745371561043
    },
    {
        "path": [
            {
                "latitude": 36.1699,
                "name": "Start",
                "longitude": -115.1398
            },
            {
                "latitude": 34.0522,
                "name": "End",
                "longitude": -118.2437
            }
        ],
        "distanceMiles": 228.4199081268248,
        "name": "Road Trip to LA",
        "distanceKm": 367.6063223530303,
        "time": 3.0455987750243305
    },
    {
        "path": [
            {
                "latitude": 40.7128,
                "name": "Start",
                "longitude": -74.006
            },
            {
                "latitude": 47.6062,
                "name": "End",
                "longitude": -122.3321
            }
        ],
        "distanceMiles": 2401.927216614402,
        "name": "NYC to Seattle",
        "distanceKm": 3865.5283503967867,
        "time": 36.95272640945234
    },
    {
        "path": [
            {
                "latitude": 37.7749,
                "name": "Start",
                "longitude": -122.4194
            },
            {
                "latitude": 37.7749,
                "name": "End",
                "longitude": -122.4194
            }
        ],
        "distanceMiles": 0,
        "name": "Teleporting Simulator",
        "distanceKm": 0,
        "time": 0
    },
    {
        "path": [
            {
                "latitude": 41.8781,
                "name": "Start",
                "longitude": -87.6298
            },
            {
                "latitude": 41.6676,
                "name": "End",
                "longitude": -88.5372
            }
        ],
        "distanceMiles": 48.967106409994805,
        "name": "Haunted Corn Maze",
        "distanceKm": 78.80494327864481,
        "time": 1.6322368803331602
    }
]